ec2/__init__.py
ec2/base.py
ec2/connection.py
ec2/helpers.py
ec2/types.py
ec2-0.4.0.dist-info/DESCRIPTION.rst
ec2-0.4.0.dist-info/METADATA
ec2-0.4.0.dist-info/metadata.json
ec2-0.4.0.dist-info/RECORD
ec2-0.4.0.dist-info/top_level.txt
ec2-0.4.0.dist-info/WHEEL
